{
  "id": "ttldursp_f1t3",
  "display_name": "Estimated Sleep Duration: Manually edited recording time of which periods of probable wake were removed based on movement, heart rate and other non-EEG signals  from type III home sleep apnea test",
  "description": "Estimated sleep duration, providing an approximation of total sleep duration (i.e. total sleep time) inferred from analysis of non-EEG channels [Zhao et al., 2017 (PMID:27707441)]( https://www.ncbi.nlm.nih.gov/pmc/articles/PMC5181603/)",
  "type": "integer",
  "units": "minutes",
  "labels": [
    "tst",
    "slpprdp",
    "ttldursp"
  ],
  "commonly_used": true
}
